deckmaster/__init__.py
deckmaster/bridge.py
deckmaster/deck_json.py
deckmaster/download.py
deckmaster/gui.py
deckmaster/gui_about_app.py
deckmaster/gui_deck.py
deckmaster/gui_menu.py
deckmaster/gui_search.py
deckmaster/gui_stats.py
deckmaster/main.py
deckmaster/printingsdb.py
deckmaster/tui.py
deckmaster-0.1.0.dist-info/METADATA
deckmaster-0.1.0.dist-info/WHEEL
deckmaster-0.1.0.dist-info/entry_points.txt
deckmaster-0.1.0.dist-info/top_level.txt
deckmaster-0.1.0.dist-info/RECORD
